{"fechaActualizacion":"2026-06-08T15:35:20","trenes":[{"codComercial":"18014","codEstAnt":"11300","codEstSig":"11300","horaLlegadaSigEst":"2026-06-08T15:33","codProduct":16,"codOrigen":"11511","codDestino":"10000","accesible":false,"ultRetraso":"3","latitud":42.89488,"longitud":-2.181059,"time":1780925719,"p":"4","mat":"449017"},{"codComercial":"00602","codEstAnt":"04007","codEstSig":"60000","horaLlegadaSigEst":"2026-06-08T16:05:20","codProduct":11,"codOrigen":"80100","codDestino":"60000","accesible":false,"ultRetraso":"1","latitud":40.442978,"longitud":-3.340706,"time":1780925714,"p":"0","mat":"120053"},{"codComercial":"00609","codEstAnt":"04007","codEstSig":"70600","horaLlegadaSigEst":"2026-06-08T16:20:10","codProduct":11,"codOrigen":"60000","codDestino":"80100","accesible":false,"ultRetraso":"-1","latitud":40.58667,"longitud":-3.1257784,"time":1780925714,"p":"0","mat":"120056"},{"codComercial":"18770","codEstAnt":"37500","codEstSig":"37500","horaLlegadaSigEst":"2026-06-08T15:21:10","codProduct":19,"codOrigen":"37200","codDestino":"37606","accesible":false,"ultRetraso":"-2","latitud":38.9215,"longitud":-6.343041,"time":1780925720,"p":"4","mat":"599021"},{"codComercial":"15782","codEstAnt":"79104","codEstSig":"79009","horaLlegadaSigEst":"2026-06-08T16:03:00","codProduct":16,"codOrigen":"79309","codDestino":"71801","accesible":false,"ultRetraso":"4","latitud":41.631134,"longitud":2.3755403,"time":1780925714,"p":"2","mat":"449016,449038"},{"codComercial":"18012","codEstAnt":"11014","codEstSig":"11000","horaLlegadaSigEst":"2026-06-08T15:17:00","codProduct":16,"codOrigen":"11511","codDestino":"10000","accesible":false,"ultRetraso":"-2","latitud":41.917606,"longitud":-4.495865,"time":1780925691,"p":"2","mat":"449025"},{"codComercial":"00606","codEstAnt":"80100","codEstSig":"80108","horaLlegadaSigEst":"2026-06-08T15:52:00","codProduct":11,"codOrigen":"80100","codDestino":"60000","accesible":false,"ultRetraso":"19","latitud":42.693012,"longitud":-1.6498513,"time":1780925714,"p":"0","mat":"120009"},{"codComercial":"17041","codEstAnt":"50002","codEstSig":"50002","horaLlegadaSigEst":"2026-06-08T15:30","codProduct":16,"codOrigen":"37200","codDestino":"17000","accesible":false,"ultRetraso":"0","latitud":39.169308,"longitud":-3.232968,"time":1780925719,"p":"4","mat":"449001"},{"codComercial":"04121","codEstAnt":"15211","codEstSig":"15410","horaLlegadaSigEst":"2026-06-08T15:52:30","codProduct":28,"codOrigen":"17000","codDestino":"15410","accesible":false,"ultRetraso":"31","latitud":43.46174,"longitud":-5.828288,"time":1780925702,"p":"1","mat":"106055"},{"codComercial":"03150","codEstAnt":"71801","codEstSig":"60000","horaLlegadaSigEst":"2026-06-08T18:26:00","codProduct":2,"codOrigen":"71801","codDestino":"60000","accesible":true,"ultRetraso":"-1","latitud":41.334167,"longitud":2.099686,"time":1780925481,"p":"1","mat":"103007"},{"codComercial":"03151","codEstAnt":"60000","codEstSig":"71801","horaLlegadaSigEst":"2026-06-08T18:02:00","codProduct":2,"codOrigen":"60000","codDestino":"71801","accesible":true,"ultRetraso":"3","latitud":40.7622,"longitud":-2.967254,"time":1780925668,"p":"1","mat":"103019"},{"codComercial":"03152","codEstAnt":"71801","codEstSig":"04040","horaLlegadaSigEst":"2026-06-08T16:26:50","codProduct":2,"codOrigen":"71801","codDestino":"60000","accesible":true,"ultRetraso":"0","latitud":41.348576,"longitud":1.1930401,"time":1780925702,"p":"1","mat":"103017"},{"codComercial":"05170","codEstAnt":"15100","codEstSig":"14100","horaLlegadaSigEst":"2026-06-08T15:58:40","codProduct":2,"codOrigen":"15100","codDestino":"03216","accesible":true,"ultRetraso":"9","latitud":42.501617,"longitud":-5.5531383,"time":1780925663,"p":"1","mat":"112007"},{"codComercial":"18777","codEstAnt":"37611","codEstSig":"37500","horaLlegadaSigEst":"2026-06-08T15:18:00","codProduct":19,"codOrigen":"37606","codDestino":"37200","accesible":false,"ultRetraso":"10","latitud":38.921597,"longitud":-6.3433747,"time":1780925712,"p":"2","mat":"599011"},{"codComercial":"71811","codEstAnt":"05311","codEstSig":"05311","horaLlegadaSigEst":"2026-06-08T15:22","codProduct":16,"codOrigen":"21010","codDestino":"15211","accesible":false,"ultRetraso":"7","latitud":43.348606,"longitud":-5.967645,"time":1780925720,"p":"4","mat":"527019"},{"codComercial":"00438","codEstAnt":"11200","codEstSig":"13200","horaLlegadaSigEst":"2026-06-08T16:46:50","codProduct":11,"codOrigen":"71801","codDestino":"13200","accesible":false,"ultRetraso":"53","latitud":43.015965,"longitud":-2.9753673,"time":1780925714,"p":"0","mat":"120057"},{"codComercial":"00437","codEstAnt":"13200","codEstSig":"11200","horaLlegadaSigEst":"2026-06-08T16:51:00","codProduct":11,"codOrigen":"13200","codDestino":"71801","accesible":true,"ultRetraso":"-1","latitud":43.071674,"longitud":-2.999547,"time":1780925714,"p":"0","mat":"120064"},{"codComercial":"03308","codEstAnt":"78400","codEstSig":"04040","horaLlegadaSigEst":"2026-06-08T15:58:20","codProduct":2,"codOrigen":"71801","codDestino":"60000","accesible":false,"ultRetraso":"13","latitud":41.52812,"longitud":-0.06462366,"time":1780925680,"p":"1","mat":"103026"},{"codComercial":"13011","codEstAnt":"50507","codEstSig":"50507","horaLlegadaSigEst":"2026-06-08T15:35","codProduct":16,"codOrigen":"51003","codDestino":"50500","accesible":false,"ultRetraso":"17","latitud":37.70739,"longitud":-5.3416224,"time":1780925719,"p":"4","mat":"449053"},{"codComercial":"18021","codEstAnt":"80108","codEstSig":"80100","horaLlegadaSigEst":"2026-06-08T15:38","codProduct":19,"codOrigen":"71100","codDestino":"11200","accesible":false,"ultRetraso":"14","latitud":42.795322,"longitud":-1.6702573,"time":1780925719,"p":"4","mat":"470177"},{"codComercial":"13010","codEstAnt":"51103","codEstSig":"51203","horaLlegadaSigEst":"2026-06-08T15:41","codProduct":16,"codOrigen":"51003","codDestino":"51405","accesible":false,"ultRetraso":"12","latitud":36.987305,"longitud":-6.0060277,"time":1780925719,"p":"4","mat":"449005"},{"codComercial":"15033","codEstAnt":"71500","codEstSig":"71500","horaLlegadaSigEst":"2026-06-08T15:35","codProduct":19,"codOrigen":"79400","codDestino":"71400","accesible":false,"ultRetraso":"23","latitud":41.111366,"longitud":1.2533424,"time":1780925719,"p":"4","mat":"448008"},{"codComercial":"71891","codEstAnt":"05763","codEstSig":"05763","horaLlegadaSigEst":"2026-06-08T15:20","codProduct":16,"codOrigen":"05803","codDestino":"05451","accesible":false,"ultRetraso":"-1","latitud":42.80892,"longitud":-5.213964,"time":1780925720,"p":"4","mat":"526013"},{"codComercial":"03305","codEstAnt":"60000","codEstSig":"70600","horaLlegadaSigEst":"2026-06-08T16:40:00","codProduct":2,"codOrigen":"60000","codDestino":"71801","accesible":false,"ultRetraso":"0","latitud":40.390385,"longitud":-3.6731367,"time":1780925702,"p":"1","mat":"103024"},{"codComercial":"17050","codEstAnt":"71401","codEstSig":"71500","horaLlegadaSigEst":"2026-06-08T15:30:00","codProduct":19,"codOrigen":"71400","codDestino":"79400","accesible":false,"ultRetraso":"6","latitud":41.110847,"longitud":1.2304701,"time":1780925714,"p":"2","mat":"447062"},{"codComercial":"05843","codEstAnt":"03410","codEstSig":"17000","horaLlegadaSigEst":"2026-06-08T16:36:00","codProduct":2,"codOrigen":"61200","codDestino":"17000","accesible":false,"ultRetraso":"-2","latitud":40.038586,"longitud":-2.150263,"time":1780925688,"p":"1","mat":"106011"},{"codComercial":"03143","codEstAnt":"60000","codEstSig":"70600","horaLlegadaSigEst":"2026-06-08T16:05:40","codProduct":2,"codOrigen":"60000","codDestino":"04307","accesible":true,"ultRetraso":"25","latitud":40.89101,"longitud":-2.7192369,"time":1780925700,"p":"1","mat":"100023"},{"codComercial":"08158","codEstAnt":"10600","codEstSig":"08004","horaLlegadaSigEst":"2026-06-08T15:55","codProduct":3,"codOrigen":"10600","codDestino":"17000","accesible":false,"ultRetraso":"0","latitud":41.302475,"longitud":-4.7143526,"time":1780925720,"p":"4","mat":"114006"},{"codComercial":"12608","codEstAnt":"22104","codEstSig":"22104","horaLlegadaSigEst":"2026-06-08T15:30","codProduct":19,"codOrigen":"22200","codDestino":"20200","accesible":false,"ultRetraso":"1","latitud":42.15492,"longitud":-8.201074,"time":1780925720,"p":"4","mat":"594005"},{"codComercial":"03141","codEstAnt":"60000","codEstSig":"71801","horaLlegadaSigEst":"2026-06-08T16:54:50","codProduct":2,"codOrigen":"60000","codDestino":"71801","accesible":false,"ultRetraso":"-5","latitud":41.53646,"longitud":-0.4716984,"time":1780925665,"p":"1","mat":"103020"},{"codComercial":"18308","codEstAnt":"32006","codEstSig":"32008","horaLlegadaSigEst":"2026-06-08T15:35:00","codProduct":16,"codOrigen":"14100","codDestino":"30110","accesible":false,"ultRetraso":"7","latitud":41.04531,"longitud":-5.5356708,"time":1780925704,"p":"2","mat":"599003"},{"codComercial":"13258","codEstAnt":"50504","codEstSig":"50506","horaLlegadaSigEst":"2026-06-08T15:40","codProduct":18,"codOrigen":"50417","codDestino":"50506","accesible":false,"ultRetraso":"-4","latitud":37.737774,"longitud":-5.2405086,"time":1780925720,"p":"4","mat":"446088"},{"codComercial":"08153","codEstAnt":"92102","codEstSig":"60000","horaLlegadaSigEst":"2026-06-08T16:02:00","codProduct":3,"codOrigen":"92102","codDestino":"60000","accesible":false,"ultRetraso":"3","latitud":40.034115,"longitud":-3.8229682,"time":1780925714,"p":"0","mat":"121006"},{"codComercial":"13013","codEstAnt":"51205","codEstSig":"51203","horaLlegadaSigEst":"2026-06-08T15:34:00","codProduct":16,"codOrigen":"51405","codDestino":"51003","accesible":false,"ultRetraso":"1","latitud":36.911922,"longitud":-6.0951147,"time":1780925716,"p":"2","mat":"449008"},{"codComercial":"08151","codEstAnt":"37200","codEstSig":"60000","horaLlegadaSigEst":"2026-06-08T16:32:40","codProduct":3,"codOrigen":"37700","codDestino":"60000","accesible":false,"ultRetraso":"8","latitud":39.08197,"longitud":-3.8951187,"time":1780925652,"p":"1","mat":"100010"},{"codComercial":"18029","codEstAnt":"11210","codEstSig":"11210","horaLlegadaSigEst":"2026-06-08T15:29:20","codProduct":19,"codOrigen":"11200","codDestino":"71100","accesible":false,"ultRetraso":"0","latitud":42.84904,"longitud":-2.5145676,"time":1780925719,"p":"4","mat":"470041"},{"codComercial":"71802","codEstAnt":"05193","codEstSig":"05193","horaLlegadaSigEst":"2026-06-08T15:00","codProduct":16,"codOrigen":"05193","codDestino":"21010","accesible":false,"ultRetraso":"0","latitud":43.536007,"longitud":-7.055802,"time":1780925720,"p":"4","mat":"527017"},{"codComercial":"18306","codEstAnt":"10504","codEstSig":"10600","horaLlegadaSigEst":"2026-06-08T15:41:00","codProduct":16,"codOrigen":"30100","codDestino":"14100","accesible":false,"ultRetraso":"4","latitud":41.608242,"longitud":-4.745956,"time":1780925713,"p":"2","mat":"599013"},{"codComercial":"71822","codEstAnt":"05551","codEstSig":"05551","horaLlegadaSigEst":"2026-06-08T15:33","codProduct":16,"codOrigen":"05571","codDestino":"15211","accesible":false,"ultRetraso":"23","latitud":43.440598,"longitud":-5.055957,"time":1780925720,"p":"4","mat":"529004"},{"codComercial":"17026","codEstAnt":"35203","codEstSig":"35200","horaLlegadaSigEst":"2026-06-08T15:52:00","codProduct":19,"codOrigen":"37500","codDestino":"18000","accesible":false,"ultRetraso":"0","latitud":39.92263,"longitud":-5.1817904,"time":1780925715,"p":"2","mat":"599043"},{"codComercial":"18076","codEstAnt":"81105","codEstSig":"81108","horaLlegadaSigEst":"2026-06-08T15:37","codProduct":19,"codOrigen":"81100","codDestino":"71100","accesible":false,"ultRetraso":"-2","latitud":42.324665,"longitud":-1.9805994,"time":1780925719,"p":"4","mat":"470140"},{"codComercial":"18073","codEstAnt":"81205","codEstSig":"81205","horaLlegadaSigEst":"2026-06-08T15:28","codProduct":19,"codOrigen":"71100","codDestino":"81100","accesible":false,"ultRetraso":"5","latitud":41.91493,"longitud":-1.4201784,"time":1780925719,"p":"4","mat":"470163"},{"codComercial":"02124","codEstAnt":"50500","codEstSig":"51003","horaLlegadaSigEst":"2026-06-08T15:23:00","codProduct":11,"codOrigen":"60000","codDestino":"51405","accesible":true,"ultRetraso":"8","latitud":37.393646,"longitud":-5.9736276,"time":1780925689,"p":"1","mat":"130033"},{"codComercial":"02123","codEstAnt":"78400","codEstSig":"04104","horaLlegadaSigEst":"2026-06-08T15:42:50","codProduct":2,"codOrigen":"60000","codDestino":"71801","accesible":true,"ultRetraso":"13","latitud":41.399277,"longitud":1.1446394,"time":1780925699,"p":"1","mat":"103025"},{"codComercial":"00622","codEstAnt":"11200","codEstSig":"11014","horaLlegadaSigEst":"2026-06-08T15:58:00","codProduct":11,"codOrigen":"71801","codDestino":"08223","accesible":false,"ultRetraso":"30","latitud":42.47304,"longitud":-3.4396744,"time":1780925660,"p":"1","mat":"130004"},{"codComercial":"00621","codEstAnt":"11014","codEstSig":"11200","horaLlegadaSigEst":"2026-06-08T16:12:20","codProduct":11,"codOrigen":"08223","codDestino":"71801","accesible":true,"ultRetraso":"17","latitud":42.45153,"longitud":-3.451463,"time":1780925720,"p":"4","mat":"130008"},{"codComercial":"05750","codEstAnt":"17000","codEstSig":"03208","horaLlegadaSigEst":"2026-06-08T16:36:10","codProduct":2,"codOrigen":"17000","codDestino":"03216","accesible":false,"ultRetraso":"3","latitud":40.468075,"longitud":-3.6830125,"time":1780925684,"p":"1","mat":"112030"},{"codComercial":"04143","codEstAnt":"10600","codEstSig":"14100","horaLlegadaSigEst":"2026-06-08T15:36","codProduct":11,"codOrigen":"60911","codDestino":"14223","accesible":true,"ultRetraso":"1","latitud":42.01267,"longitud":-4.529436,"time":1780925719,"p":"4","mat":"130003"},{"codComercial":"08744","codEstAnt":"02002","codEstSig":"50500","horaLlegadaSigEst":"2026-06-08T15:58:10","codProduct":3,"codOrigen":"54413","codDestino":"51003","accesible":false,"ultRetraso":"7","latitud":37.505913,"longitud":-4.867763,"time":1780925586,"p":"2","mat":"104004"},{"codComercial":"12538","codEstAnt":"22300","codEstSig":"23000","horaLlegadaSigEst":"2026-06-08T15:36:00","codProduct":18,"codOrigen":"22308","codDestino":"31400","accesible":false,"ultRetraso":"22","latitud":42.28577,"longitud":-8.609822,"time":1780925716,"p":"2","mat":"599032"},{"codComercial":"02122","codEstAnt":"54413","codEstSig":"54413","horaLlegadaSigEst":"2026-06-08T15:41:10","codProduct":2,"codOrigen":"60000","codDestino":"54413","accesible":true,"ultRetraso":"6","latitud":36.697887,"longitud":-4.4617906,"time":1780925692,"p":"1","mat":"112004"},{"codComercial":"04140","codEstAnt":"15410","codEstSig":"15211","horaLlegadaSigEst":"2026-06-08T15:54:00","codProduct":11,"codOrigen":"15410","codDestino":"60911","accesible":true,"ultRetraso":"1","latitud":43.53815,"longitud":-5.7288637,"time":1780925681,"p":"1","mat":"130031"},{"codComercial":"09157","codEstAnt":"03412","codEstSig":"03410","horaLlegadaSigEst":"2026-06-08T15:36:20","codProduct":3,"codOrigen":"61200","codDestino":"60911","accesible":false,"ultRetraso":"7","latitud":38.231026,"longitud":-0.7868739,"time":1780925717,"p":"2","mat":"104010"},{"codComercial":"01152","codEstAnt":"65000","codEstSig":"65300","horaLlegadaSigEst":"2026-06-08T15:49","codProduct":10,"codOrigen":"65000","codDestino":"04307","accesible":true,"ultRetraso":"1","latitud":39.767788,"longitud":-0.20285663,"time":1780925720,"p":"4","mat":"130030"},{"codComercial":"13905","codEstAnt":"01009","codEstSig":"01009","horaLlegadaSigEst":"2026-06-08T15:26","codProduct":16,"codOrigen":"02003","codDestino":"51003","accesible":false,"ultRetraso":"18","latitud":37.22228,"longitud":-4.893699,"time":1780925719,"p":"4","mat":"598001"},{"codComercial":"04142","codEstAnt":"14213","codEstSig":"14100","horaLlegadaSigEst":"2026-06-08T16:44:00","codProduct":11,"codOrigen":"14223","codDestino":"17000","accesible":true,"ultRetraso":"16","latitud":42.898567,"longitud":-4.143016,"time":1780925687,"p":"1","mat":"130027"},{"codComercial":"09155","codEstAnt":"03412","codEstSig":"62002","horaLlegadaSigEst":"2026-06-08T15:34:50","codProduct":3,"codOrigen":"60911","codDestino":"61200","accesible":false,"ultRetraso":"5","latitud":38.078785,"longitud":-0.9428383,"time":1780925717,"p":"2","mat":"104001"},{"codComercial":"09550","codEstAnt":"22100","codEstSig":"31400","horaLlegadaSigEst":"2026-06-08T16:08:00","codProduct":3,"codOrigen":"22100","codDestino":"31412","accesible":false,"ultRetraso":"0","latitud":42.36103,"longitud":-7.9209495,"time":1780925714,"p":"0","mat":"121018"},{"codComercial":"09153","codEstAnt":"31412","codEstSig":"31400","horaLlegadaSigEst":"2026-06-08T15:34:00","codProduct":16,"codOrigen":"31412","codDestino":"08223","accesible":false,"ultRetraso":"5","latitud":42.870995,"longitud":-8.543436,"time":1780925714,"p":"0","mat":"121007"},{"codComercial":"15009","codEstAnt":"71304","codEstSig":"71303","horaLlegadaSigEst":"2026-06-08T15:31:00","codProduct":19,"codOrigen":"79400","codDestino":"71210","accesible":false,"ultRetraso":"15","latitud":41.136784,"longitud":0.80289346,"time":1780925715,"p":"2","mat":"447104"},{"codComercial":"18004","codEstAnt":"10409","codEstSig":"10400","horaLlegadaSigEst":"2026-06-08T15:55:00","codProduct":16,"codOrigen":"10600","codDestino":"10000","accesible":false,"ultRetraso":"10","latitud":40.968773,"longitud":-4.6381817,"time":1780925713,"p":"2","mat":"449046"},{"codComercial":"18126","codEstAnt":"71600","codEstSig":"71801","horaLlegadaSigEst":"2026-06-08T15:40","codProduct":19,"codOrigen":"65400","codDestino":"79400","accesible":false,"ultRetraso":"3","latitud":41.26706,"longitud":1.9571081,"time":1780925719,"p":"4","mat":"448020"},{"codComercial":"71832","codEstAnt":"05321","codEstSig":"05321","horaLlegadaSigEst":"2026-06-08T15:33","codProduct":16,"codOrigen":"15211","codDestino":"21010","accesible":false,"ultRetraso":"9","latitud":43.448746,"longitud":-6.0771136,"time":1780925720,"p":"4","mat":"527013"},{"codComercial":"18127","codEstAnt":"65420","codEstSig":"65420","horaLlegadaSigEst":"2026-06-08T15:34","codProduct":19,"codOrigen":"79400","codDestino":"65400","accesible":false,"ultRetraso":"18","latitud":40.999844,"longitud":0.9126038,"time":1780925719,"p":"4","mat":"470114,470187"},{"codComercial":"17031","codEstAnt":"37606","codEstSig":"35400","horaLlegadaSigEst":"2026-06-08T16:00","codProduct":16,"codOrigen":"37606","codDestino":"35400","accesible":true,"ultRetraso":"19","latitud":38.94897,"longitud":-6.413811,"time":1780925720,"p":"4","mat":"730016"},{"codComercial":"15013","codEstAnt":"71801","codEstSig":"71801","horaLlegadaSigEst":"2026-06-08T15:31","codProduct":19,"codOrigen":"79400","codDestino":"71400","accesible":false,"ultRetraso":"0","latitud":41.379074,"longitud":2.139723,"time":1780925719,"p":"4","mat":"448006"},{"codComercial":"15011","codEstAnt":"71600","codEstSig":"71600","horaLlegadaSigEst":"2026-06-08T15:29","codProduct":19,"codOrigen":"79400","codDestino":"71400","accesible":false,"ultRetraso":"11","latitud":41.185974,"longitud":1.524699,"time":1780925719,"p":"4","mat":"448021"},{"codComercial":"00694","codEstAnt":"60600","codEstSig":"64100","horaLlegadaSigEst":"2026-06-08T16:15:50","codProduct":11,"codOrigen":"50300","codDestino":"71801","accesible":true,"ultRetraso":"1","latitud":38.872166,"longitud":-1.1129868,"time":1780925704,"p":"1","mat":"130045"},{"codComercial":"04257","codEstAnt":"17000","codEstSig":"10600","horaLlegadaSigEst":"2026-06-08T15:44:40","codProduct":13,"codOrigen":"17000","codDestino":"11511","accesible":true,"ultRetraso":"-1","latitud":41.516865,"longitud":-4.7689385,"time":1780925714,"p":"0","mat":"121016"},{"codComercial":"05742","codEstAnt":"03208","codEstSig":"60600","horaLlegadaSigEst":"2026-06-08T16:02:20","codProduct":2,"codOrigen":"60000","codDestino":"61200","accesible":false,"ultRetraso":"4","latitud":39.94103,"longitud":-2.0409446,"time":1780925673,"p":"1","mat":"112012"},{"codComercial":"00697","codEstAnt":"60400","codEstSig":"50100","horaLlegadaSigEst":"2026-06-08T15:43:50","codProduct":11,"codOrigen":"71801","codDestino":"50300","accesible":true,"ultRetraso":"6","latitud":39.141827,"longitud":-3.2386198,"time":1780925677,"p":"1","mat":"130043"},{"codComercial":"04254","codEstAnt":"22100","codEstSig":"30200","horaLlegadaSigEst":"2026-06-08T16:31:30","codProduct":2,"codOrigen":"08223","codDestino":"17000","accesible":false,"ultRetraso":"3","latitud":42.25695,"longitud":-7.8212414,"time":1780925637,"p":"1","mat":"106058"},{"codComercial":"08335","codEstAnt":"05012","codEstSig":"05000","horaLlegadaSigEst":"2026-06-08T15:38:10","codProduct":3,"codOrigen":"51003","codDestino":"05000","accesible":false,"ultRetraso":"13","latitud":37.19375,"longitud":-3.641478,"time":1780925719,"p":"4","mat":"104020"},{"codComercial":"03162","codEstAnt":"79300","codEstSig":"71801","horaLlegadaSigEst":"2026-06-08T15:54:00","codProduct":2,"codOrigen":"04307","codDestino":"60000","accesible":true,"ultRetraso":"4","latitud":41.620594,"longitud":2.3688257,"time":1780925707,"p":"1","mat":"103023"},{"codComercial":"15810","codEstAnt":"79302","codEstSig":"79303","horaLlegadaSigEst":"2026-06-08T15:35:00","codProduct":18,"codOrigen":"71801","codDestino":"79315","accesible":false,"ultRetraso":"1","latitud":42.04404,"longitud":2.94493,"time":1780925712,"p":"2","mat":"447025"},{"codComercial":"09143","codEstAnt":"23004","codEstSig":"08224","horaLlegadaSigEst":"2026-06-08T15:34:30","codProduct":16,"codOrigen":"31412","codDestino":"08223","accesible":true,"ultRetraso":"1","latitud":42.286022,"longitud":-8.603778,"time":1780925714,"p":"0","mat":"121012"},{"codComercial":"09142","codEstAnt":"31400","codEstSig":"31412","horaLlegadaSigEst":"2026-06-08T16:02:50","codProduct":16,"codOrigen":"08223","codDestino":"31412","accesible":false,"ultRetraso":"3","latitud":42.89703,"longitud":-8.504579,"time":1780925714,"p":"0","mat":"121011"},{"codComercial":"14443","codEstAnt":"65311","codEstSig":"65308","horaLlegadaSigEst":"2026-06-08T15:32:00","codProduct":18,"codOrigen":"65312","codDestino":"65300","accesible":false,"ultRetraso":"12","latitud":40.312706,"longitud":0.23200218,"time":1780925717,"p":"2","mat":"447005"},{"codComercial":"14202","codEstAnt":"61307","codEstSig":"61307","horaLlegadaSigEst":"2026-06-08T13:01","codProduct":16,"codOrigen":"61307","codDestino":"65000","accesible":false,"ultRetraso":"-192","latitud":37.605175,"longitud":-0.97484106,"time":1780925720,"p":"4","mat":"599006,599015"},{"codComercial":"09140","codEstAnt":"31400","codEstSig":"31412","horaLlegadaSigEst":"2026-06-08T15:42:00","codProduct":3,"codOrigen":"22100","codDestino":"31412","accesible":true,"ultRetraso":"4","latitud":43.326195,"longitud":-8.446349,"time":1780925714,"p":"0","mat":"121024"},{"codComercial":"15814","codEstAnt":"79104","codEstSig":"79200","horaLlegadaSigEst":"2026-06-08T15:44:00","codProduct":16,"codOrigen":"71801","codDestino":"79309","accesible":false,"ultRetraso":"0","latitud":41.693455,"longitud":2.4990203,"time":1780925717,"p":"3","mat":"449040,449042"},{"codComercial":"18128","codEstAnt":"65402","codEstSig":"65402","horaLlegadaSigEst":"2026-06-08T15:19","codProduct":19,"codOrigen":"65400","codDestino":"79400","accesible":false,"ultRetraso":"2","latitud":40.753696,"longitud":0.6141503,"time":1780925719,"p":"4","mat":"448004,448014"},{"codComercial":"18129","codEstAnt":"71801","codEstSig":"71600","horaLlegadaSigEst":"2026-06-08T15:46:00","codProduct":19,"codOrigen":"79400","codDestino":"65400","accesible":false,"ultRetraso":"-2","latitud":41.22414,"longitud":1.7750443,"time":1780925717,"p":"3","mat":"449034"},{"codComercial":"15812","codEstAnt":"79203","codEstSig":"79300","horaLlegadaSigEst":"2026-06-08T15:39:00","codProduct":16,"codOrigen":"71801","codDestino":"79300","accesible":false,"ultRetraso":"3","latitud":41.862663,"longitud":2.8078835,"time":1780925707,"p":"2","mat":"449020,449024"},{"codComercial":"18214","codEstAnt":"15007","codEstSig":"15006","horaLlegadaSigEst":"2026-06-08T15:39:00","codProduct":19,"codOrigen":"15100","codDestino":"14100","accesible":false,"ultRetraso":"6","latitud":42.217255,"longitud":-4.9214225,"time":1780925715,"p":"2","mat":"449037"},{"codComercial":"18330","codEstAnt":"60400","codEstSig":"50100","horaLlegadaSigEst":"2026-06-08T15:48:00","codProduct":16,"codOrigen":"60400","codDestino":"37606","accesible":false,"ultRetraso":"1","latitud":39.27515,"longitud":-3.2082567,"time":1780925695,"p":"2","mat":"599004"},{"codComercial":"18171","codEstAnt":"18000","codEstSig":"18000","horaLlegadaSigEst":"2026-06-08T15:25","codProduct":16,"codOrigen":"60400","codDestino":"17000","accesible":false,"ultRetraso":"-1","latitud":40.406128,"longitud":-3.689053,"time":1780925719,"p":"4","mat":"449044"},{"codComercial":"04325","codEstAnt":"08251","codEstSig":"22100","horaLlegadaSigEst":"2026-06-08T16:15:00","codProduct":11,"codOrigen":"17000","codDestino":"20309","accesible":true,"ultRetraso":"0","latitud":42.064045,"longitud":-7.135253,"time":1780925704,"p":"1","mat":"730018"},{"codComercial":"08525","codEstAnt":"50500","codEstSig":"51003","horaLlegadaSigEst":"2026-06-08T15:56:10","codProduct":3,"codOrigen":"05000","codDestino":"51003","accesible":false,"ultRetraso":"6","latitud":37.58747,"longitud":-5.6477804,"time":1780925713,"p":"2","mat":"104003"},{"codComercial":"02149","codEstAnt":"02002","codEstSig":"50500","horaLlegadaSigEst":"2026-06-08T15:39:30","codProduct":28,"codOrigen":"54413","codDestino":"60000","accesible":false,"ultRetraso":"2","latitud":37.841625,"longitud":-4.935873,"time":1780925685,"p":"1","mat":"112020"},{"codComercial":"18170","codEstAnt":"50100","codEstSig":"94002","horaLlegadaSigEst":"2026-06-08T15:37:10","codProduct":16,"codOrigen":"17000","codDestino":"37200","accesible":false,"ultRetraso":"19","latitud":39.05344,"longitud":-3.57234,"time":1780925719,"p":"4","mat":"449056"},{"codComercial":"02140","codEstAnt":"60000","codEstSig":"50500","horaLlegadaSigEst":"2026-06-08T15:56:20","codProduct":2,"codOrigen":"60000","codDestino":"51003","accesible":true,"ultRetraso":"12","latitud":38.325287,"longitud":-4.552717,"time":1780925707,"p":"1","mat":"100006"},{"codComercial":"09730","codEstAnt":"04040","codEstSig":"60000","horaLlegadaSigEst":"2026-06-08T16:27:00","codProduct":2,"codOrigen":"87089","codDestino":"60000","accesible":false,"ultRetraso":"9","latitud":40.906517,"longitud":-2.6803985,"time":1780925665,"p":"1","mat":"100022"},{"codComercial":"02142","codEstAnt":"60000","codEstSig":"50500","horaLlegadaSigEst":"2026-06-08T17:04:20","codProduct":2,"codOrigen":"60000","codDestino":"54413","accesible":true,"ultRetraso":"25","latitud":40.395203,"longitud":-3.6738262,"time":1780925565,"p":"1","mat":"102002"},{"codComercial":"02141","codEstAnt":"50500","codEstSig":"60000","horaLlegadaSigEst":"2026-06-08T17:25:30","codProduct":2,"codOrigen":"51003","codDestino":"60000","accesible":true,"ultRetraso":"17","latitud":37.92135,"longitud":-4.70273,"time":1780925687,"p":"1","mat":"100005"},{"codComercial":"15866","codEstAnt":"79301","codEstSig":"79300","horaLlegadaSigEst":"2026-06-08T15:41:00","codProduct":18,"codOrigen":"79315","codDestino":"71801","accesible":false,"ultRetraso":"1","latitud":42.026093,"longitud":2.8467004,"time":1780925714,"p":"2","mat":"447029"},{"codComercial":"04958","codEstAnt":"30100","codEstSig":"08240","horaLlegadaSigEst":"2026-06-08T16:08:00","codProduct":11,"codOrigen":"30100","codDestino":"17000","accesible":false,"ultRetraso":"1","latitud":41.039444,"longitud":-5.5452404,"time":1780925714,"p":"0","mat":"121023"},{"codComercial":"17012","codEstAnt":"35002","codEstSig":"35005","horaLlegadaSigEst":"2026-06-08T15:43:10","codProduct":19,"codOrigen":"18000","codDestino":"37500","accesible":false,"ultRetraso":"20","latitud":40.244404,"longitud":-3.8388577,"time":1780925715,"p":"2","mat":"599002"},{"codComercial":"14022","codEstAnt":"65208","codEstSig":"65208","horaLlegadaSigEst":"2026-06-08T15:29:30","codProduct":19,"codOrigen":"65400","codDestino":"65000","accesible":false,"ultRetraso":"12","latitud":39.932945,"longitud":-0.09655001,"time":1780925720,"p":"4","mat":"470019"},{"codComercial":"02137","codEstAnt":"37200","codEstSig":"60000","horaLlegadaSigEst":"2026-06-08T16:17:20","codProduct":28,"codOrigen":"51003","codDestino":"60000","accesible":false,"ultRetraso":"10","latitud":39.671703,"longitud":-3.799574,"time":1780925700,"p":"1","mat":"112019"},{"codComercial":"18061","codEstAnt":"11300","codEstSig":"11306","horaLlegadaSigEst":"2026-06-08T15:54:00","codProduct":16,"codOrigen":"10000","codDestino":"11511","accesible":false,"ultRetraso":"22","latitud":42.897747,"longitud":-2.1821728,"time":1780925713,"p":"2","mat":"449039"},{"codComercial":"02136","codEstAnt":"50500","codEstSig":"02030","horaLlegadaSigEst":"2026-06-08T16:13:20","codProduct":2,"codOrigen":"60000","codDestino":"05000","accesible":false,"ultRetraso":"3","latitud":37.791348,"longitud":-4.9989753,"time":1780925654,"p":"1","mat":"102010"},{"codComercial":"18063","codEstAnt":"10500","codEstSig":"10600","horaLlegadaSigEst":"2026-06-08T15:55:00","codProduct":16,"codOrigen":"10000","codDestino":"11511","accesible":false,"ultRetraso":"39","latitud":41.339523,"longitud":-4.8825784,"time":1780925713,"p":"2","mat":"449052"},{"codComercial":"02135","codEstAnt":"51003","codEstSig":"50500","horaLlegadaSigEst":"2026-06-08T16:13:10","codProduct":11,"codOrigen":"51405","codDestino":"60000","accesible":false,"ultRetraso":"16","latitud":37.46597,"longitud":-5.9530206,"time":1780925714,"p":"0","mat":"120065"},{"codComercial":"09725","codEstAnt":"04040","codEstSig":"04104","horaLlegadaSigEst":"2026-06-08T15:49:00","codProduct":2,"codOrigen":"60000","codDestino":"87089","accesible":false,"ultRetraso":"11","latitud":41.476948,"longitud":0.8830264,"time":1780925666,"p":"1","mat":"100021"},{"codComercial":"02133","codEstAnt":"50500","codEstSig":"60000","horaLlegadaSigEst":"2026-06-08T15:56:20","codProduct":2,"codOrigen":"54413","codDestino":"60000","accesible":false,"ultRetraso":"7","latitud":40.18933,"longitud":-3.7502728,"time":1780925647,"p":"1","mat":"103002"},{"codComercial":"04151","codEstAnt":"08004","codEstSig":"10600","horaLlegadaSigEst":"2026-06-08T15:59:10","codProduct":2,"codOrigen":"17000","codDestino":"15410","accesible":false,"ultRetraso":"0","latitud":41.030327,"longitud":-4.3493695,"time":1780925669,"p":"1","mat":"106064"},{"codComercial":"18907","codEstAnt":"10000","codEstSig":"10200","horaLlegadaSigEst":"2026-06-08T16:02:00","codProduct":16,"codOrigen":"10000","codDestino":"30110","accesible":false,"ultRetraso":"3","latitud":40.45341,"longitud":-3.802328,"time":1780925715,"p":"2","mat":"599038"},{"codComercial":"15918","codEstAnt":"79009","codEstSig":"79004","horaLlegadaSigEst":"2026-06-08T15:38","codProduct":18,"codOrigen":"71801","codDestino":"79315","accesible":false,"ultRetraso":"9","latitud":41.420265,"longitud":2.1942494,"time":1780925720,"p":"4","mat":"447173"},{"codComercial":"01162","codEstAnt":"60911","codEstSig":"65000","horaLlegadaSigEst":"2026-06-08T15:53:00","codProduct":10,"codOrigen":"60911","codDestino":"71801","accesible":true,"ultRetraso":"27","latitud":39.278828,"longitud":-0.43037403,"time":1780925667,"p":"1","mat":"130007"},{"codComercial":"02130","codEstAnt":"50500","codEstSig":"51003","horaLlegadaSigEst":"2026-06-08T15:48:20","codProduct":2,"codOrigen":"60000","codDestino":"51003","accesible":false,"ultRetraso":"9","latitud":37.532753,"longitud":-5.881303,"time":1780925720,"p":"4","mat":"100001"},{"codComercial":"14302","codEstAnt":"65208","codEstSig":"65208","horaLlegadaSigEst":"2026-06-08T15:27:40","codProduct":18,"codOrigen":"65000","codDestino":"65400","accesible":false,"ultRetraso":"21","latitud":39.932945,"longitud":-0.09655001,"time":1780925720,"p":"4","mat":"470115"},{"codComercial":"18903","codEstAnt":"30100","codEstSig":"30100","horaLlegadaSigEst":"2026-06-08T14:03","codProduct":16,"codOrigen":"10000","codDestino":"30110","accesible":false,"ultRetraso":"10","latitud":40.971676,"longitud":-5.648387,"time":1780925720,"p":"4","mat":"599007"},{"codComercial":"18905","codEstAnt":"10400","codEstSig":"34010","horaLlegadaSigEst":"2026-06-08T16:06:00","codProduct":16,"codOrigen":"10000","codDestino":"30110","accesible":false,"ultRetraso":"12","latitud":40.728027,"longitud":-4.7383666,"time":1780925713,"p":"2","mat":"599001"},{"codComercial":"15510","codEstAnt":"04040","codEstSig":"70806","horaLlegadaSigEst":"2026-06-08T15:20:00","codProduct":19,"codOrigen":"04040","codDestino":"78400","accesible":false,"ultRetraso":"1","latitud":41.743393,"longitud":-0.8335293,"time":1780925704,"p":"2","mat":"594004"},{"codComercial":"17104","codEstAnt":"10207","codEstSig":"10209","horaLlegadaSigEst":"2026-06-08T15:37:00","codProduct":18,"codOrigen":"10400","codDestino":"10203","accesible":false,"ultRetraso":"3","latitud":40.55361,"longitud":-4.3000765,"time":1780925716,"p":"2","mat":"465066"},{"codComercial":"02167","codEstAnt":"05000","codEstSig":"02030","horaLlegadaSigEst":"2026-06-08T15:40:40","codProduct":2,"codOrigen":"05000","codDestino":"02003","accesible":true,"ultRetraso":"-4","latitud":37.11658,"longitud":-4.42876,"time":1780925593,"p":"1","mat":"102008"},{"codComercial":"04345","codEstAnt":"17000","codEstSig":"30200","horaLlegadaSigEst":"2026-06-08T15:41:50","codProduct":2,"codOrigen":"17000","codDestino":"31412","accesible":false,"ultRetraso":"-2","latitud":41.51798,"longitud":-5.525837,"time":1780925669,"p":"1","mat":"106063"},{"codComercial":"05951","codEstAnt":"03216","codEstSig":"03213","horaLlegadaSigEst":"2026-06-08T15:42:50","codProduct":2,"codOrigen":"65300","codDestino":"60000","accesible":false,"ultRetraso":"9","latitud":39.44678,"longitud":-0.7703707,"time":1780925679,"p":"1","mat":"100002"},{"codComercial":"03930","codEstAnt":"50500","codEstSig":"02030","horaLlegadaSigEst":"2026-06-08T15:36:30","codProduct":2,"codOrigen":"50500","codDestino":"05000","accesible":true,"ultRetraso":"52","latitud":37.02961,"longitud":-4.570414,"time":1780925697,"p":"1","mat":"102006"},{"codComercial":"14517","codEstAnt":"61303","codEstSig":"61200","horaLlegadaSigEst":"2026-06-08T15:41","codProduct":16,"codOrigen":"61307","codDestino":"61200","accesible":false,"ultRetraso":"10","latitud":37.976032,"longitud":-1.0885359,"time":1780925720,"p":"4","mat":"592055"},{"codComercial":"05152","codEstAnt":"17000","codEstSig":"60911","horaLlegadaSigEst":"2026-06-08T17:25:30","codProduct":2,"codOrigen":"17000","codDestino":"60911","accesible":true,"ultRetraso":"8","latitud":40.473335,"longitud":-3.680902,"time":1780925624,"p":"1","mat":"112015"},{"codComercial":"17907","codEstAnt":"37500","codEstSig":"35400","horaLlegadaSigEst":"2026-06-08T16:30:00","codProduct":16,"codOrigen":"51003","codDestino":"18000","accesible":false,"ultRetraso":"20","latitud":38.92159,"longitud":-6.3433137,"time":1780925716,"p":"2","mat":"599049"},{"codComercial":"03130","codEstAnt":"71801","codEstSig":"60000","horaLlegadaSigEst":"2026-06-08T16:32:00","codProduct":2,"codOrigen":"71801","codDestino":"60000","accesible":true,"ultRetraso":"3","latitud":41.03176,"longitud":-2.4556365,"time":1780925626,"p":"1","mat":"103004"},{"codComercial":"02163","codEstAnt":"54413","codEstSig":"02003","horaLlegadaSigEst":"2026-06-08T15:53:50","codProduct":2,"codOrigen":"54413","codDestino":"60000","accesible":true,"ultRetraso":"2","latitud":36.702675,"longitud":-4.50613,"time":1780925707,"p":"1","mat":"102007"},{"codComercial":"12696","codEstAnt":"20305","codEstSig":"20300","horaLlegadaSigEst":"2026-06-08T15:39:20","codProduct":16,"codOrigen":"20309","codDestino":"22100","accesible":false,"ultRetraso":"7","latitud":42.541065,"longitud":-7.4996433,"time":1780925713,"p":"2","mat":"594106"},{"codComercial":"12455","codEstAnt":"23010","codEstSig":"23010","horaLlegadaSigEst":"2026-06-08T15:33","codProduct":18,"codOrigen":"31400","codDestino":"22308","accesible":false,"ultRetraso":"1","latitud":42.72287,"longitud":-8.651964,"time":1780925719,"p":"4","mat":"599040"},{"codComercial":"17902","codEstAnt":"37500","codEstSig":"40002","horaLlegadaSigEst":"2026-06-08T15:41:40","codProduct":16,"codOrigen":"18000","codDestino":"51003","accesible":false,"ultRetraso":"5","latitud":38.922134,"longitud":-6.354413,"time":1780925715,"p":"2","mat":"599044"},{"codComercial":"09351","codEstAnt":"31412","codEstSig":"31400","horaLlegadaSigEst":"2026-06-08T15:43:00","codProduct":3,"codOrigen":"31412","codDestino":"22100","accesible":true,"ultRetraso":"4","latitud":43.01077,"longitud":-8.448188,"time":1780925714,"p":"0","mat":"121022"},{"codComercial":"04181","codEstAnt":"60911","codEstSig":"03309","horaLlegadaSigEst":"2026-06-08T15:46:20","codProduct":11,"codOrigen":"60911","codDestino":"15410","accesible":true,"ultRetraso":"1","latitud":38.407852,"longitud":-0.66102606,"time":1780925690,"p":"1","mat":"130009"},{"codComercial":"17501","codEstAnt":"71105","codEstSig":"71100","horaLlegadaSigEst":"2026-06-08T15:33","codProduct":19,"codOrigen":"71300","codDestino":"04040","accesible":false,"ultRetraso":"45","latitud":41.623585,"longitud":-0.85520744,"time":1780925720,"p":"4","mat":"448002"},{"codComercial":"14516","codEstAnt":"61303","codEstSig":"61303","horaLlegadaSigEst":"2026-06-08T15:20","codProduct":18,"codOrigen":"61200","codDestino":"61307","accesible":false,"ultRetraso":"11","latitud":37.818768,"longitud":-0.95074505,"time":1780925720,"p":"4","mat":"592015"},{"codComercial":"13942","codEstAnt":"57003","codEstSig":"57003","horaLlegadaSigEst":"2026-06-08T15:35","codProduct":16,"codOrigen":"05000","codDestino":"56310","accesible":false,"ultRetraso":"3","latitud":37.39583,"longitud":-3.5277848,"time":1780925719,"p":"4","mat":"599020"},{"codComercial":"18048","codEstAnt":"70807","codEstSig":"71100","horaLlegadaSigEst":"2026-06-08T15:35:00","codProduct":19,"codOrigen":"81200","codDestino":"71100","accesible":false,"ultRetraso":"0","latitud":41.640553,"longitud":-0.8828275,"time":1780925713,"p":"3","mat":"449012"},{"codComercial":"15052","codEstAnt":"71600","codEstSig":"71801","horaLlegadaSigEst":"2026-06-08T16:15:00","codProduct":19,"codOrigen":"78400","codDestino":"79400","accesible":false,"ultRetraso":"8","latitud":41.196808,"longitud":1.6426407,"time":1780925703,"p":"2","mat":"447158"},{"codComercial":"71876","codEstAnt":"05483","codEstSig":"05721","horaLlegadaSigEst":"2026-06-08T15:40:30","codProduct":16,"codOrigen":"05451","codDestino":"05803","accesible":false,"ultRetraso":"3","latitud":43.191284,"longitud":-3.1955986,"time":1780925720,"p":"4","mat":"527001"},{"codComercial":"71872","codEstAnt":"05687","codEstSig":"05687","horaLlegadaSigEst":"2026-06-08T15:26:20","codProduct":16,"codOrigen":"05451","codDestino":"05663","accesible":false,"ultRetraso":"16","latitud":43.346546,"longitud":-3.421043,"time":1780925720,"p":"4","mat":"524027"},{"codComercial":"13032","codEstAnt":"50600","codEstSig":"51003","horaLlegadaSigEst":"2026-06-08T15:43:00","codProduct":16,"codOrigen":"50500","codDestino":"51003","accesible":false,"ultRetraso":"6","latitud":37.424637,"longitud":-5.9510736,"time":1780925714,"p":"2","mat":"449019"},{"codComercial":"18040","codEstAnt":"60200","codEstSig":"60203","horaLlegadaSigEst":"2026-06-08T15:35:00","codProduct":16,"codOrigen":"17000","codDestino":"60600","accesible":false,"ultRetraso":"8","latitud":39.88043,"longitud":-3.729637,"time":1780925715,"p":"2","mat":"449036"},{"codComercial":"01101","codEstAnt":"65000","codEstSig":"60911","horaLlegadaSigEst":"2026-06-08T16:14:00","codProduct":10,"codOrigen":"04307","codDestino":"60911","accesible":true,"ultRetraso":"34","latitud":38.596127,"longitud":-0.8572622,"time":1780925673,"p":"1","mat":"130028"},{"codComercial":"02156","codEstAnt":"60000","codEstSig":"37200","horaLlegadaSigEst":"2026-06-08T15:52:00","codProduct":28,"codOrigen":"60000","codDestino":"51003","accesible":false,"ultRetraso":"-1","latitud":39.452763,"longitud":-3.8187075,"time":1780925708,"p":"1","mat":"112025"},{"codComercial":"01463","codEstAnt":"65000","codEstSig":"64100","horaLlegadaSigEst":"2026-06-08T15:54:20","codProduct":13,"codOrigen":"65000","codDestino":"61307","accesible":true,"ultRetraso":"9","latitud":39.213707,"longitud":-0.4400915,"time":1780925719,"p":"4","mat":"252048,6B7"},{"codComercial":"03122","codEstAnt":"60000","codEstSig":"60000","horaLlegadaSigEst":"2026-06-08T15:48:00","codProduct":2,"codOrigen":"71801","codDestino":"60000","accesible":true,"ultRetraso":"4","latitud":40.381546,"longitud":-3.6811278,"time":1780925671,"p":"1","mat":"103013"},{"codComercial":"09742","codEstAnt":"87374","codEstSig":"04307","horaLlegadaSigEst":"2026-06-08T18:21:00","codProduct":2,"codOrigen":"87303","codDestino":"71801","accesible":false,"ultRetraso":"0","latitud":44.17234,"longitud":4.7257166,"time":1780925645,"p":"1","mat":"100020"},{"codComercial":"34113","codEstAnt":"71801","codEstSig":"79300","horaLlegadaSigEst":"2026-06-08T15:52:10","codProduct":10,"codOrigen":"71801","codDestino":"04307","accesible":true,"ultRetraso":"11","latitud":41.67432,"longitud":2.4437575,"time":1780925680,"p":"1","mat":"130036"},{"codComercial":"05140","codEstAnt":"17000","codEstSig":"03208","horaLlegadaSigEst":"2026-06-08T15:41:00","codProduct":2,"codOrigen":"17000","codDestino":"03216","accesible":false,"ultRetraso":"8","latitud":40.044853,"longitud":-2.362275,"time":1780925685,"p":"1","mat":"112003"},{"codComercial":"01460","codEstAnt":"60905","codEstSig":"60905","horaLlegadaSigEst":"2026-06-08T15:30:50","codProduct":13,"codOrigen":"61307","codDestino":"65000","accesible":true,"ultRetraso":"8","latitud":38.48479,"longitud":-0.80087405,"time":1780925719,"p":"4","mat":"252070,6B3"},{"codComercial":"05143","codEstAnt":"60600","codEstSig":"03208","horaLlegadaSigEst":"2026-06-08T16:04:20","codProduct":2,"codOrigen":"60911","codDestino":"17000","accesible":true,"ultRetraso":"1","latitud":39.04702,"longitud":-1.8997031,"time":1780925705,"p":"1","mat":"112016"},{"codComercial":"02152","codEstAnt":"60000","codEstSig":"54413","horaLlegadaSigEst":"2026-06-08T18:25:10","codProduct":2,"codOrigen":"60000","codDestino":"54413","accesible":false,"ultRetraso":"1","latitud":40.398853,"longitud":-3.6766558,"time":1780925669,"p":"1","mat":"102013"},{"codComercial":"05142","codEstAnt":"60600","codEstSig":"03309","horaLlegadaSigEst":"2026-06-08T16:07:10","codProduct":2,"codOrigen":"17000","codDestino":"60911","accesible":true,"ultRetraso":"0","latitud":38.999657,"longitud":-1.8468211,"time":1780925675,"p":"1","mat":"112017"},{"codComercial":"12100","codEstAnt":"15200","codEstSig":"15200","horaLlegadaSigEst":"2026-06-08T15:27","codProduct":18,"codOrigen":"15410","codDestino":"10600","accesible":false,"ultRetraso":"10","latitud":43.205975,"longitud":-5.7923346,"time":1780925719,"p":"4","mat":"440217"},{"codComercial":"14003","codEstAnt":"65000","codEstSig":"64100","horaLlegadaSigEst":"2026-06-08T16:14:20","codProduct":19,"codOrigen":"65000","codDestino":"60911","accesible":false,"ultRetraso":"1","latitud":39.40003,"longitud":-0.39904568,"time":1780925719,"p":"4","mat":"470118"},{"codComercial":"14405","codEstAnt":"64100","codEstSig":"60800","horaLlegadaSigEst":"2026-06-08T15:47:30","codProduct":16,"codOrigen":"65000","codDestino":"60600","accesible":false,"ultRetraso":"18","latitud":38.77773,"longitud":-0.90519136,"time":1780925657,"p":"3","mat":"599014"},{"codComercial":"13955","codEstAnt":"56200","codEstSig":"05000","horaLlegadaSigEst":"2026-06-08T15:58:00","codProduct":16,"codOrigen":"56310","codDestino":"05000","accesible":false,"ultRetraso":"-2","latitud":37.395775,"longitud":-3.5278275,"time":1780925717,"p":"2","mat":"599010"}]}